yoptapy/__init__.py
yoptapy/yoptapy.py
yoptapy-0.1.1.dist-info/METADATA
yoptapy-0.1.1.dist-info/WHEEL
yoptapy-0.1.1.dist-info/RECORD
