Metadata-Version: 2.4
Name: yoptapy
Version: 0.1.1
Summary: Йоптапай, инструмент для реальных пацанов
Author-email: Dickson <hhatedme@gmail.com>
License-Expression: MIT
Keywords: gopnik,python,translator
Requires-Python: >=3.6
